pytest_lobster/__init__.py
pytest_lobster/lobster.py
pytest_lobster-0.2.3.dist-info/METADATA
pytest_lobster-0.2.3.dist-info/WHEEL
pytest_lobster-0.2.3.dist-info/entry_points.txt
pytest_lobster-0.2.3.dist-info/licenses/LICENSE
pytest_lobster-0.2.3.dist-info/RECORD
